nanosimpy/__init__.py
nanosimpy/brownian_cy.pyx
nanosimpy/brownian_domain_trap_cy.pyx
nanosimpy/brownian_domain_trap_cy.so
nanosimpy/brownian_trap_cy.pyx
nanosimpy/brownian_trap_cy.so
nanosimpy/brownian_trap_hop_cy.pyx
nanosimpy/brownian_trap_hop_cy.so
nanosimpy/correlation_methods.py
nanosimpy/equations_to_fit.py
nanosimpy/extra_fn.py
nanosimpy/input_and_output.py
nanosimpy/integrate_over_psf_adv_cy.pyx
nanosimpy/setup.py
nanosimpy/simulation_methods.py
nanosimpy/brownian_trap_cy/pyx.so
nanosimpy-0.0.1.dist-info/DESCRIPTION.rst
nanosimpy-0.0.1.dist-info/METADATA
nanosimpy-0.0.1.dist-info/RECORD
nanosimpy-0.0.1.dist-info/WHEEL
nanosimpy-0.0.1.dist-info/metadata.json
nanosimpy-0.0.1.dist-info/top_level.txt
