Metadata-Version: 2.0
Name: nanosimpy
Version: 0.0.1
Summary: The nano simulation python libary
Home-page: https://github.com/dwaithe/nanosimpy
Author: Dominic Waithe
Author-email: dominic_waithe@hotmail.com
License: MIT
Platform: UNKNOWN
Requires-Dist: cython
Requires-Dist: matplotlib
Requires-Dist: numpy
Requires-Dist: scipy
Requires-Dist: tifffile
